napari_svg/__init__.py
napari_svg/_shape_to_xml.py
napari_svg/_version.py
napari_svg/hook_implementations.py
napari_svg/layer_to_xml.py
napari_svg/napari.yaml
napari_svg/xml_to_svg.py
napari_svg/_tests/__init__.py
napari_svg/_tests/test_get_writer.py
napari_svg/_tests/test_write_layer.py
napari_svg/_tests/test_write_points_with_attributes-expected.svg
napari_svg-0.2.0.dist-info/LICENSE
napari_svg-0.2.0.dist-info/METADATA
napari_svg-0.2.0.dist-info/WHEEL
napari_svg-0.2.0.dist-info/entry_points.txt
napari_svg-0.2.0.dist-info/top_level.txt
napari_svg-0.2.0.dist-info/RECORD
