Metadata-Version: 2.1
Name: napari-svg
Version: 0.2.0
Summary: A plugin for writing svg files with napari
Author-email: Nicholas Sofroniew <sofroniewn@gmail.com>, napari core devs <napari-core-devs@googlegroups.com>
License: BSD-3
Project-URL: Source, https://github.com/napari/napari-svg
Project-URL: Bug Tracker, https://github.com/napari/napari-svg/issues
Classifier: Development Status :: 4 - Beta
Classifier: Intended Audience :: Developers
Classifier: Framework :: napari
Classifier: Topic :: Software Development :: Testing
Classifier: Programming Language :: Python
Classifier: Programming Language :: Python :: 3
Classifier: Programming Language :: Python :: 3.9
Classifier: Programming Language :: Python :: 3.10
Classifier: Programming Language :: Python :: 3.11
Classifier: Programming Language :: Python :: 3.12
Classifier: Operating System :: OS Independent
Classifier: License :: OSI Approved :: BSD License
Requires-Python: >=3.9
License-File: LICENSE
Requires-Dist: imageio >=2.5.0
Requires-Dist: numpy >=1.16.0
Requires-Dist: vispy >=0.6.4
Provides-Extra: testing
Requires-Dist: napari >=0.4 ; extra == 'testing'
Requires-Dist: pyqt5 ; extra == 'testing'
Requires-Dist: pytest ; extra == 'testing'
Requires-Dist: pytest-cov ; extra == 'testing'
